edc_analytics/__init__.py
edc_analytics/apps.py
edc_analytics/constants.py
edc_analytics/custom_tables/__init__.py
edc_analytics/custom_tables/age.py
edc_analytics/custom_tables/art.py
edc_analytics/custom_tables/bmi.py
edc_analytics/custom_tables/bp.py
edc_analytics/custom_tables/fasting.py
edc_analytics/custom_tables/fbg.py
edc_analytics/custom_tables/fbg_ogtt.py
edc_analytics/custom_tables/gender.py
edc_analytics/custom_tables/hba1c.py
edc_analytics/custom_tables/ogtt.py
edc_analytics/custom_tables/waist.py
edc_analytics/data.py
edc_analytics/row/__init__.py
edc_analytics/row/row_definition.py
edc_analytics/row/row_definitions.py
edc_analytics/row/row_statistics.py
edc_analytics/row/row_statistics_with_gender.py
edc_analytics/stata/__init__.py
edc_analytics/stata/get_stata_labels_from_model.py
edc_analytics/styler.py
edc_analytics/table.py
edc_analytics/tests/__init__.py
edc_analytics/tests/test_tables.py
edc_analytics/urls.py
edc_analytics-1.0.2.dist-info/licenses/LICENSE
edc_analytics-1.0.2.dist-info/WHEEL
edc_analytics-1.0.2.dist-info/METADATA
edc_analytics-1.0.2.dist-info/RECORD
